{"name":"GET  list of category","id":"category;get--list-of-category","testSteps":[{"number":1,"description":"Given I set the GET api endpoints","duration":191,"startTime":"2023-05-07T12:04:10.856499400+07:00[Asia/Jakarta]","result":"SUCCESS","precondition":false,"level":0,"children":[{"number":2,"description":"I set the GET api endpoints","duration":0,"startTime":"2023-05-07T12:04:11.043997400+07:00[Asia/Jakarta]","result":"SUCCESS","precondition":false,"level":1}]},{"number":3,"description":"When I send HTTP api GET request","duration":238,"startTime":"2023-05-07T12:04:11.049979400+07:00[Asia/Jakarta]","result":"SUCCESS","precondition":false,"level":0,"children":[{"number":4,"description":"I send HTTP api GET request","duration":232,"startTime":"2023-05-07T12:04:11.051974500+07:00[Asia/Jakarta]","result":"SUCCESS","precondition":false,"level":1,"children":[{"number":5,"description":"I set the GET api endpoints","duration":0,"startTime":"2023-05-07T12:04:11.056968700+07:00[Asia/Jakarta]","result":"SUCCESS","precondition":false,"level":2},{"number":6,"description":"GET https://altashop-api.fly.dev/api/categories","duration":0,"startTime":"2023-05-07T12:04:11.283355300+07:00[Asia/Jakarta]","result":"SUCCESS","restQuery":{"method":"GET","path":"https://altashop-api.fly.dev/api/categories","content":"","contentType":"null","requestHeaders":"Accept\u003d*/*","requestCookies":"","responseHeaders":"content-type: application/json\r\ndate: Sun, 07 May 2023 05:04:12 GMT\r\ntransfer-encoding: chunked\r\ncontent-encoding: gzip\r\nserver: Fly/3f2597ca (2023-05-03)\r\nvia: 1.1 fly.io\r\nfly-request-id: 01GZT9H4NR475MR49HREQTK41B-sin\r","responseCookies":"\r","responseBody":"{\n    \"data\": [\n        {\n            \"ID\": 12505,\n            \"Name\": \"Furniture\",\n            \"Description\": \"for gaming purposes\"\n        },\n        {\n            \"ID\": 12508,\n            \"Name\": \"Furniture\",\n            \"Description\": \"for gaming purposes\"\n        },\n        {\n            \"ID\": 12509,\n            \"Name\": \"!@#$%\",\n            \"Description\": \"for gaming purposes\"\n        },\n        {\n            \"ID\": 12511,\n            \"Name\": \"gaming\",\n            \"Description\": \"for gaming purposes\"\n        },\n        {\n            \"ID\": 12513,\n            \"Name\": \"gaming\",\n            \"Description\": \"for gaming purposes\"\n        },\n        {\n            \"ID\": 12514,\n            \"Name\": \"gaming\",\n            \"Description\": \"for gaming purposes\"\n        },\n        {\n            \"ID\": 12516,\n            \"Name\": \"gaming\",\n            \"Description\": \"for gaming purposes\"\n        },\n        {\n            \"ID\": 12517,\n            \"Name\": \"gaming\",\n            \"Description\": \"for gaming purposes\"\n        },\n        {\n            \"ID\": 12519,\n            \"Name\": \"gaming\",\n            \"Description\": \"for gaming purposes\"\n        },\n        {\n            \"ID\": 12520,\n            \"Name\": \"gaming\",\n            \"Description\": \"for gaming purposes\"\n        },\n        {\n            \"ID\": 12522,\n            \"Name\": \"gaming\",\n            \"Description\": \"for gaming purposes\"\n        },\n        {\n            \"ID\": 12523,\n            \"Name\": \"Veterinary\",\n            \"Description\": \"electrician\"\n        },\n        {\n            \"ID\": 12525,\n            \"Name\": \"Motion Pictures and Film\",\n            \"Description\": \"hairdresser\"\n        },\n        {\n            \"ID\": 12527,\n            \"Name\": \"Human Resources\",\n            \"Description\": \"window cleaner\"\n        },\n        {\n            \"ID\": 12529,\n            \"Name\": \"Education Management\",\n            \"Description\": \"police officer\"\n        },\n        {\n            \"ID\": 12531,\n            \"Name\": \"Railroad Manufacture\",\n            \"Description\": \"attorney at law\"\n        },\n        {\n            \"ID\": 12533,\n            \"Name\": \"Batagor Woku\",\n            \"Description\": \"Cemilan sehat lezat bergizi\"\n        },\n        {\n            \"ID\": 12534,\n            \"Name\": \"gaming\",\n            \"Description\": \"for gaming purposes\"\n        },\n        {\n            \"ID\": 12535,\n            \"Name\": \"gamingg\",\n            \"Description\": \"for gaming purposes\"\n        },\n        {\n            \"ID\": 12536,\n            \"Name\": \"testes\",\n            \"Description\": \"\"\n        },\n        {\n            \"ID\": 12538,\n            \"Name\": \"gamingg\",\n            \"Description\": \"for gaming purposes\"\n        },\n        {\n            \"ID\": 12539,\n            \"Name\": \"testes\",\n            \"Description\": \"\"\n        },\n        {\n            \"ID\": 12541,\n            \"Name\": \"Gaming\",\n            \"Description\": \"For gaming purposes\"\n        },\n        {\n            \"ID\": 12542,\n            \"Name\": \"Gaming\",\n            \"Description\": \"\"\n        },\n        {\n            \"ID\": 12543,\n            \"Name\": \"gamingg\",\n            \"Description\": \"for gaming purposes\"\n        },\n        {\n            \"ID\": 12544,\n            \"Name\": \"testes\",\n            \"Description\": \"\"\n        },\n        {\n            \"ID\": 12547,\n            \"Name\": \"Gaming\",\n            \"Description\": \"\"\n        },\n        {\n            \"ID\": 12551,\n            \"Name\": \"gaming\",\n            \"Description\": \"for gaming purposes\"\n        },\n        {\n            \"ID\": 12552,\n            \"Name\": \"gaming\",\n            \"Description\": \"for gaming purposes\"\n        },\n        {\n            \"ID\": 12553,\n            \"Name\": \"Batagor Woku\",\n            \"Description\": \"Cemilan sehat lezat bergizi\"\n        },\n        {\n            \"ID\": 12554,\n            \"Name\": \"Batagor Woku\",\n            \"Description\": \"Cemilan sehat lezat bergizi\"\n        },\n        {\n            \"ID\": 12555,\n            \"Name\": \"Batagor Woku\",\n            \"Description\": \"Cemilan sehat lezat bergizi\"\n        },\n        {\n            \"ID\": 12556,\n            \"Name\": \"Batagor Woku\",\n            \"Description\": \"Cemilan sehat lezat bergizi\"\n        },\n        {\n            \"ID\": 12557,\n            \"Name\": \"Batagor Woku\",\n            \"Description\": \"Cemilan sehat lezat bergizi\"\n        },\n        {\n            \"ID\": 12558,\n            \"Name\": \"Batagor Woku\",\n            \"Description\": \"Cemilan sehat lezat bergizi\"\n        },\n        {\n            \"ID\": 12559,\n            \"Name\": \"Batagor Woku\",\n            \"Description\": \"Cemilan sehat lezat bergizi\"\n        },\n        {\n            \"ID\": 12560,\n            \"Name\": \"gaming\",\n            \"Description\": \"for gaming purposes\"\n        },\n        {\n            \"ID\": 12561,\n            \"Name\": \"Akbar Rizky Fahrurozy\",\n            \"Description\": \"mini project\"\n        },\n        {\n            \"ID\": 12562,\n            \"Name\": \"Batagor Woku\",\n            \"Description\": \"Cemilan sehat lezat bergizi\"\n        },\n        {\n            \"ID\": 12563,\n            \"Name\": \"gaming\",\n            \"Description\": \"for gaming purposes\"\n        },\n        {\n            \"ID\": 12564,\n            \"Name\": \"gaming\",\n            \"Description\": \"for gaming purposes\"\n        },\n        {\n            \"ID\": 12565,\n            \"Name\": \"Batagor Woku\",\n            \"Description\": \"Cemilan sehat lezat bergizi\"\n        },\n        {\n            \"ID\": 12566,\n            \"Name\": \"gaming\",\n            \"Description\": \"for gaming purposes\"\n        },\n        {\n            \"ID\": 12567,\n            \"Name\": \"Category Aulia\",\n            \"Description\": \"ini category aulia\"\n        },\n        {\n            \"ID\": 12568,\n            \"Name\": \"nama produk\",\n            \"Description\": \"kategori produk\"\n        },\n        {\n            \"ID\": 12569,\n            \"Name\": \"Batagor Woku\",\n            \"Description\": \"Cemilan sehat lezat bergizi\"\n        },\n        {\n            \"ID\": 12571,\n            \"Name\": \"gaming\",\n            \"Description\": \"for gaming purposes\"\n        },\n        {\n            \"ID\": 12572,\n            \"Name\": \"gaming\",\n            \"Description\": \"for gaming purposes\"\n        },\n        {\n            \"ID\": 12573,\n            \"Name\": \"gaming\",\n            \"Description\": \"for gaming purposes\"\n        },\n        {\n            \"ID\": 12574,\n            \"Name\": \"gaming\",\n            \"Description\": \"for gaming purposes\"\n        },\n        {\n            \"ID\": 12575,\n            \"Name\": \"gaming\",\n            \"Description\": \"for gaming purposes\"\n        },\n        {\n            \"ID\": 12576,\n            \"Name\": \"gaming\",\n            \"Description\": \"for gaming purposes\"\n        },\n        {\n            \"ID\": 12578,\n            \"Name\": \"gaming\",\n            \"Description\": \"for gaming purposes\"\n        },\n        {\n            \"ID\": 12579,\n            \"Name\": \"gamingg\",\n            \"Description\": \"for gaming purposes\"\n        },\n        {\n            \"ID\": 12580,\n            \"Name\": \"testes\",\n            \"Description\": \"\"\n        },\n        {\n            \"ID\": 12582,\n            \"Name\": \"gaming\",\n            \"Description\": \"for gaming purposes\"\n        },\n        {\n            \"ID\": 12583,\n            \"Name\": \"gaming\",\n            \"Description\": \"for gaming purposes\"\n        },\n        {\n            \"ID\": 12584,\n            \"Name\": \"testes\",\n            \"Description\": \"\"\n        },\n        {\n            \"ID\": 12586,\n            \"Name\": \"gaming\",\n            \"Description\": \"for gaming purposes\"\n        },\n        {\n            \"ID\": 12587,\n            \"Name\": \"testes\",\n            \"Description\": \"\"\n        },\n        {\n            \"ID\": 12589,\n            \"Name\": \"gaming\",\n            \"Description\": \"for gaming purposes\"\n        },\n        {\n            \"ID\": 12590,\n            \"Name\": \"Test\",\n            \"Description\": \"Ini Testing Giel\"\n        },\n        {\n            \"ID\": 12591,\n            \"Name\": \"gaming\",\n            \"Description\": \"for gaming purposes\"\n        },\n        {\n            \"ID\": 12592,\n            \"Name\": \"gaming\",\n            \"Description\": \"for gaming purposes\"\n        },\n        {\n            \"ID\": 12593,\n            \"Name\": \"gaming\",\n            \"Description\": \"for gaming purposes\"\n        },\n        {\n            \"ID\": 12594,\n            \"Name\": \"gaming\",\n            \"Description\": \"for gaming purposes\"\n        },\n        {\n            \"ID\": 12595,\n            \"Name\": \"gaming\",\n            \"Description\": \"for gaming purposes\"\n        },\n        {\n            \"ID\": 12596,\n            \"Name\": \"gaming\",\n            \"Description\": \"for gaming purposes\"\n        },\n        {\n            \"ID\": 12597,\n            \"Name\": \"gaming\",\n            \"Description\": \"for gaming purposes\"\n        },\n        {\n            \"ID\": 12598,\n            \"Name\": \"gaming\",\n            \"Description\": \"for gaming purposes\"\n        },\n        {\n            \"ID\": 12599,\n            \"Name\": \"testes\",\n            \"Description\": \"\"\n        },\n        {\n            \"ID\": 12601,\n            \"Name\": \"gaming\",\n            \"Description\": \"for gaming purposes\"\n        },\n        {\n            \"ID\": 12602,\n            \"Name\": \"testes\",\n            \"Description\": \"\"\n        },\n        {\n            \"ID\": 12604,\n            \"Name\": \"gaming\",\n            \"Description\": \"for gaming purposes\"\n        },\n        {\n            \"ID\": 12605,\n            \"Name\": \"testes\",\n            \"Description\": \"\"\n        },\n        {\n            \"ID\": 12607,\n            \"Name\": \"gaming\",\n            \"Description\": \"for gaming purposes\"\n        },\n        {\n            \"ID\": 12608,\n            \"Name\": \"testes\",\n            \"Description\": \"\"\n        },\n        {\n            \"ID\": 12611,\n            \"Name\": \"makanan\",\n            \"Description\": \"makanan\"\n        },\n        {\n            \"ID\": 12612,\n            \"Name\": \"gaming\",\n            \"Description\": \"for gaming purposes\"\n        },\n        {\n            \"ID\": 12613,\n            \"Name\": \"gaming\",\n            \"Description\": \"for gaming purposes\"\n        },\n        {\n            \"ID\": 12614,\n            \"Name\": \"gaming\",\n            \"Description\": \"for gaming purposes\"\n        },\n        {\n            \"ID\": 12615,\n            \"Name\": \"gaming\",\n            \"Description\": \"for gaming purposes\"\n        },\n        {\n            \"ID\": 12616,\n            \"Name\": \"gaming\",\n            \"Description\": \"for gaming purposes\"\n        },\n        {\n            \"ID\": 12617,\n            \"Name\": \"Batagor Woku\",\n            \"Description\": \"Cemilan sehat lezat bergizi\"\n        },\n        {\n            \"ID\": 12618,\n            \"Name\": \"Wireless\",\n            \"Description\": \"physicist\"\n        },\n        {\n            \"ID\": 12620,\n            \"Name\": \"gaming\",\n            \"Description\": \"for gaming purposes\"\n        },\n        {\n            \"ID\": 12622,\n            \"Name\": \"gaming\",\n            \"Description\": \"for gaming purposes\"\n        },\n        {\n            \"ID\": 12624,\n            \"Name\": \"gaming\",\n            \"Description\": \"for gaming purposes\"\n        },\n        {\n            \"ID\": 12626,\n            \"Name\": \"gaming\",\n            \"Description\": \"for gaming purposes\"\n        },\n        {\n            \"ID\": 12628,\n            \"Name\": \"gaming\",\n            \"Description\": \"asd\"\n        },\n        {\n            \"ID\": 12629,\n            \"Name\": \"testing product\",\n            \"Description\": \"this is the product description\"\n        },\n        {\n            \"ID\": 12630,\n            \"Name\": \"testing product\",\n            \"Description\": \"this is the product description\"\n        },\n        {\n            \"ID\": 12631,\n            \"Name\": \"testing product\",\n            \"Description\": \"\"\n        },\n        {\n            \"ID\": 12632,\n            \"Name\": \"testing product\",\n            \"Description\": \"this is the product description\"\n        },\n        {\n            \"ID\": 12633,\n            \"Name\": \"testing product\",\n            \"Description\": \"\"\n        },\n        {\n            \"ID\": 12635,\n            \"Name\": \"gaming\",\n            \"Description\": \"for gaming purposes\"\n        },\n        {\n            \"ID\": 12636,\n            \"Name\": \"testing product\",\n            \"Description\": \"this is the product description\"\n        },\n        {\n            \"ID\": 12637,\n            \"Name\": \"testing product\",\n            \"Description\": \"\"\n        },\n        {\n            \"ID\": 12641,\n            \"Name\": \"testing product\",\n            \"Description\": \"this is the product description\"\n        },\n        {\n            \"ID\": 12642,\n            \"Name\": \"testing product\",\n            \"Description\": \"\"\n        },\n        {\n            \"ID\": 12644,\n            \"Name\": \"gaming\",\n            \"Description\": \"for gaming purposes\"\n        },\n        {\n            \"ID\": 12646,\n            \"Name\": \"gaming\",\n            \"Description\": \"for gaming purposes\"\n        },\n        {\n            \"ID\": 12648,\n            \"Name\": \"gaming\",\n            \"Description\": \"for gaming purposes\"\n        },\n        {\n            \"ID\": 12650,\n            \"Name\": \"gaming\",\n            \"Description\": \"for gaming purposes\"\n        },\n        {\n            \"ID\": 12652,\n            \"Name\": \"gaming\",\n            \"Description\": \"for gaming purposes\"\n        },\n        {\n            \"ID\": 12653,\n            \"Name\": \"testing product\",\n            \"Description\": \"this is the product description\"\n        },\n        {\n            \"ID\": 12655,\n            \"Name\": \"gaming\",\n            \"Description\": \"for gaming purposes\"\n        },\n        {\n            \"ID\": 12656,\n            \"Name\": \"Poliwrath\",\n            \"Description\": \"Repudiandae nesciunt excepturi dolore eum sequi.\"\n        },\n        {\n            \"ID\": 12657,\n            \"Name\": \"Machoke\",\n            \"Description\": \"Quasi fuga non quod impedit velit.\"\n        },\n        {\n            \"ID\": 12658,\n            \"Name\": \"gaming\",\n            \"Description\": \"for gaming purposes\"\n        },\n        {\n            \"ID\": 12660,\n            \"Name\": \"gaming\",\n            \"Description\": \"for gaming purposes\"\n        },\n        {\n            \"ID\": 12662,\n            \"Name\": \"gamingg\",\n            \"Description\": \"for gaming purposes\"\n        },\n        {\n            \"ID\": 12663,\n            \"Name\": \"testes\",\n            \"Description\": \"\"\n        },\n        {\n            \"ID\": 12665,\n            \"Name\": \"123 aja\",\n            \"Description\": \"for merch purposes\"\n        },\n        {\n            \"ID\": 12666,\n            \"Name\": \"gaming\",\n            \"Description\": \"for gaming purposes\"\n        },\n        {\n            \"ID\": 12669,\n            \"Name\": \"gaming\",\n            \"Description\": \"for gaming purposes\"\n        },\n        {\n            \"ID\": 12670,\n            \"Name\": \"gaming\",\n            \"Description\": \"for gaming purposes\"\n        },\n        {\n            \"ID\": 12673,\n            \"Name\": \"gaming\",\n            \"Description\": \"for gaming purposes\"\n        },\n        {\n            \"ID\": 12674,\n            \"Name\": \"gaming\",\n            \"Description\": \"for gaming purposes\"\n        },\n        {\n            \"ID\": 12677,\n            \"Name\": \"gaming\",\n            \"Description\": \"for gaming purposes\"\n        },\n        {\n            \"ID\": 12680,\n            \"Name\": \"gaming\",\n            \"Description\": \"for gaming purposes\"\n        },\n        {\n            \"ID\": 12683,\n            \"Name\": \"gaming\",\n            \"Description\": \"for gaming purposes\"\n        },\n        {\n            \"ID\": 12686,\n            \"Name\": \"gaming\",\n            \"Description\": \"for gaming purposes\"\n        },\n        {\n            \"ID\": 12687,\n            \"Name\": \"gaming\",\n            \"Description\": \"\"\n        },\n        {\n            \"ID\": 12691,\n            \"Name\": \"gaming\",\n            \"Description\": \"for gaming purposes\"\n        },\n        {\n            \"ID\": 12692,\n            \"Name\": \"gaming\",\n            \"Description\": \"\"\n        },\n        {\n            \"ID\": 12696,\n            \"Name\": \"gaming\",\n            \"Description\": \"for gaming purposes\"\n        },\n        {\n            \"ID\": 12697,\n            \"Name\": \"gaming\",\n            \"Description\": \"\"\n        },\n        {\n            \"ID\": 12701,\n            \"Name\": \"gaming\",\n            \"Description\": \"for gaming purposes\"\n        },\n        {\n            \"ID\": 12702,\n            \"Name\": \"gaming\",\n            \"Description\": \"for gaming purposes\"\n        },\n        {\n            \"ID\": 12703,\n            \"Name\": \"gaming\",\n            \"Description\": \"for gaming purposes\"\n        },\n        {\n            \"ID\": 12704,\n            \"Name\": \"gaming\",\n            \"Description\": \"for gaming purposes\"\n        },\n        {\n            \"ID\": 12705,\n            \"Name\": \"gaming\",\n            \"Description\": \"for gaming purposes\"\n        },\n        {\n            \"ID\": 12706,\n            \"Name\": \"gaming\",\n            \"Description\": \"for gaming purposes\"\n        },\n        {\n            \"ID\": 12707,\n            \"Name\": \"gaming\",\n            \"Description\": \"\"\n        },\n        {\n            \"ID\": 12711,\n            \"Name\": \"gaming\",\n            \"Description\": \"for gaming purposes\"\n        },\n        {\n            \"ID\": 12712,\n            \"Name\": \"gaming\",\n            \"Description\": \"for gaming purposes\"\n        },\n        {\n            \"ID\": 12713,\n            \"Name\": \"Gaming\",\n            \"Description\": \"For gaming purposes\"\n        },\n        {\n            \"ID\": 12715,\n            \"Name\": \"Gaming\",\n            \"Description\": \"For gaming purposes\"\n        },\n        {\n            \"ID\": 12717,\n            \"Name\": \"Gaming\",\n            \"Description\": \"\"\n        },\n        {\n            \"ID\": 12718,\n            \"Name\": \"gaming\",\n            \"Description\": \"for gaming purposes\"\n        },\n        {\n            \"ID\": 12719,\n            \"Name\": \"gaming\",\n            \"Description\": \"\"\n        },\n        {\n            \"ID\": 12723,\n            \"Name\": \"Gaming\",\n            \"Description\": \"For gaming purposes\"\n        },\n        {\n            \"ID\": 12724,\n            \"Name\": \"Gaming\",\n            \"Description\": \"\"\n        },\n        {\n            \"ID\": 12726,\n            \"Name\": \"gaming\",\n            \"Description\": \"for gaming purposes\"\n        },\n        {\n            \"ID\": 12727,\n            \"Name\": \"gaming\",\n            \"Description\": \"\"\n        },\n        {\n            \"ID\": 12731,\n            \"Name\": \"gaming\",\n            \"Description\": \"for gaming purposes\"\n        },\n        {\n            \"ID\": 12732,\n            \"Name\": \"gaming\",\n            \"Description\": \"\"\n        },\n        {\n            \"ID\": 12736,\n            \"Name\": \"gaming\",\n            \"Description\": \"for gaming purposes\"\n        },\n        {\n            \"ID\": 12737,\n            \"Name\": \"gaming\",\n            \"Description\": \"\"\n        },\n        {\n            \"ID\": 12741,\n            \"Name\": \"gaming\",\n            \"Description\": \"for gaming purposes\"\n        },\n        {\n            \"ID\": 12742,\n            \"Name\": \"gaming\",\n            \"Description\": \"\"\n        },\n        {\n            \"ID\": 12746,\n            \"Name\": \"testing product\",\n            \"Description\": \"this is the product description\"\n        },\n        {\n            \"ID\": 12747,\n            \"Name\": \"testing product\",\n            \"Description\": \"\"\n        },\n        {\n            \"ID\": 12749,\n            \"Name\": \"testing product\",\n            \"Description\": \"this is the product description\"\n        },\n        {\n            \"ID\": 12751,\n            \"Name\": \"Gaming\",\n            \"Description\": \"For gaming purposes\"\n        },\n        {\n            \"ID\": 12752,\n            \"Name\": \"Gaming\",\n            \"Description\": \"\"\n        },\n        {\n            \"ID\": 12754,\n            \"Name\": \"Gaming\",\n            \"Description\": \"For gaming purposes\"\n        },\n        {\n            \"ID\": 12755,\n            \"Name\": \"Gaming\",\n            \"Description\": \"\"\n        },\n        {\n            \"ID\": 12757,\n            \"Name\": \"gaming\",\n            \"Description\": \"for gaming purposes\"\n        },\n        {\n            \"ID\": 12758,\n            \"Name\": \"Gaming\",\n            \"Description\": \"For gaming purposes\"\n        },\n        {\n            \"ID\": 12759,\n            \"Name\": \"Gaming\",\n            \"Description\": \"\"\n        },\n        {\n            \"ID\": 12761,\n            \"Name\": \"Batagor Woku\",\n            \"Description\": \"Cemilan sehat lezat bergizi\"\n        },\n        {\n            \"ID\": 12762,\n            \"Name\": \"gaming\",\n            \"Description\": \"for gaming purposes\"\n        },\n        {\n            \"ID\": 12763,\n            \"Name\": \"gaming\",\n            \"Description\": \"for gaming purposes\"\n        },\n        {\n            \"ID\": 12764,\n            \"Name\": \"Furniture\",\n            \"Description\": \"Furniture Jepara\"\n        },\n        {\n            \"ID\": 12766,\n            \"Name\": \"gaming\",\n            \"Description\": \"for gaming purposes\"\n        },\n        {\n            \"ID\": 12767,\n            \"Name\": \"gaming\",\n            \"Description\": \"for gaming purposes\"\n        },\n        {\n            \"ID\": 12770,\n            \"Name\": \"gaming\",\n            \"Description\": \"for gaming purposes\"\n        },\n        {\n            \"ID\": 12771,\n            \"Name\": \"gaming\",\n            \"Description\": \"for gaming purposes\"\n        },\n        {\n            \"ID\": 12772,\n            \"Name\": \"gaming\",\n            \"Description\": \"for gaming purposes\"\n        },\n        {\n            \"ID\": 12773,\n            \"Name\": \"Furniture\",\n            \"Description\": \"Furniture Jepara\"\n        },\n        {\n            \"ID\": 12775,\n            \"Name\": \"gaming\",\n            \"Description\": \"for gaming purposes\"\n        },\n        {\n            \"ID\": 12776,\n            \"Name\": \"Fruit\",\n            \"Description\": \"\"\n        },\n        {\n            \"ID\": 12777,\n            \"Name\": \"gaming\",\n            \"Description\": \"for gaming purposes\"\n        },\n        {\n            \"ID\": 12778,\n            \"Name\": \"Fruit\",\n            \"Description\": \"\"\n        },\n        {\n            \"ID\": 12779,\n            \"Name\": \"Fruit\",\n            \"Description\": \"good for health\"\n        },\n        {\n            \"ID\": 12780,\n            \"Name\": \"gaming\",\n            \"Description\": \"for gaming purposes\"\n        },\n        {\n            \"ID\": 12781,\n            \"Name\": \"gaming\",\n            \"Description\": \"for gaming purposes\"\n        },\n        {\n            \"ID\": 12782,\n            \"Name\": \"gaming\",\n            \"Description\": \"for gaming purposes\"\n        },\n        {\n            \"ID\": 12783,\n            \"Name\": \"gaming\",\n            \"Description\": \"for gaming purposes\"\n        },\n        {\n            \"ID\": 12784,\n            \"Name\": \"gaming\",\n            \"Description\": \"for gaming purposes\"\n        },\n        {\n            \"ID\": 12785,\n            \"Name\": \"gaming\",\n            \"Description\": \"for gaming purposes\"\n        },\n        {\n            \"ID\": 12786,\n            \"Name\": \"gaming\",\n            \"Description\": \"for gaming purposes\"\n        },\n        {\n            \"ID\": 12787,\n            \"Name\": \"gaming\",\n            \"Description\": \"for gaming purposes\"\n        },\n        {\n            \"ID\": 12788,\n            \"Name\": \"gaming\",\n            \"Description\": \"for gaming purposes\"\n        },\n        {\n            \"ID\": 12790,\n            \"Name\": \"gaming\",\n            \"Description\": \"for gaming purposes\"\n        },\n        {\n            \"ID\": 12791,\n            \"Name\": \"gaming\",\n            \"Description\": \"for gaming purposes\"\n        },\n        {\n            \"ID\": 12792,\n            \"Name\": \"gaming\",\n            \"Description\": \"for gaming purposes\"\n        },\n        {\n            \"ID\": 12793,\n            \"Name\": \"Batagor Woku\",\n            \"Description\": \"Cemilan sehat lezat bergizi\"\n        },\n        {\n            \"ID\": 12794,\n            \"Name\": \"gaming\",\n            \"Description\": \"for gaming purposes\"\n        },\n        {\n            \"ID\": 12795,\n            \"Name\": \"gaming\",\n            \"Description\": \"for gaming purposes\"\n        },\n        {\n            \"ID\": 12796,\n            \"Name\": \"gaming\",\n            \"Description\": \"\"\n        },\n        {\n            \"ID\": 12797,\n            \"Name\": \"Batagor Woku\",\n            \"Description\": \"Cemilan sehat lezat bergizi\"\n        },\n        {\n            \"ID\": 12798,\n            \"Name\": \"gaming\",\n            \"Description\": \"for gaming purposes\"\n        },\n        {\n            \"ID\": 12799,\n            \"Name\": \"gaming\",\n            \"Description\": \"for gaming purposes\"\n        },\n        {\n            \"ID\": 12800,\n            \"Name\": \"gaming\",\n            \"Description\": \"for gaming purposes\"\n        },\n        {\n            \"ID\": 12801,\n            \"Name\": \"gaming\",\n            \"Description\": \"for gaming purposes\"\n        },\n        {\n            \"ID\": 12805,\n            \"Name\": \"makanan\",\n            \"Description\": \"makanan\"\n        },\n        {\n            \"ID\": 12807,\n            \"Name\": \"GAMING\",\n            \"Description\": \"for gaming purposes\"\n        },\n        {\n            \"ID\": 12808,\n            \"Name\": \"Accessories\",\n            \"Description\": \"to enhance appearance\"\n        },\n        {\n            \"ID\": 12810,\n            \"Name\": \"Batagor Woku\",\n            \"Description\": \"Cemilan sehat lezat bergizi\"\n        },\n        {\n            \"ID\": 12811,\n            \"Name\": \"gaming\",\n            \"Description\": \"for gaming purposes\"\n        },\n        {\n            \"ID\": 12812,\n            \"Name\": \"Batagor Woku\",\n            \"Description\": \"Cemilan sehat lezat bergizi\"\n        },\n        {\n            \"ID\": 12813,\n            \"Name\": \"Batagor Woku\",\n            \"Description\": \"Cemilan sehat lezat bergizi\"\n        },\n        {\n            \"ID\": 12815,\n            \"Name\": \"Accessories\",\n            \"Description\": \"to enhance appearance\"\n        },\n        {\n            \"ID\": 12817,\n            \"Name\": \"Accessories\",\n            \"Description\": \"to enhance appearance\"\n        },\n        {\n            \"ID\": 12821,\n            \"Name\": \"Accessories\",\n            \"Description\": \"to enhance appearance\"\n        },\n        {\n            \"ID\": 12809,\n            \"Name\": \"gaming\",\n            \"Description\": \"for gaming purposes\"\n        },\n        {\n            \"ID\": 12816,\n            \"Name\": \"gaming\",\n            \"Description\": \"for gaming purposes\"\n        },\n        {\n            \"ID\": 12818,\n            \"Name\": \"gaming\",\n            \"Description\": \"for gaming purposes\"\n        },\n        {\n            \"ID\": 12819,\n            \"Name\": \"gaming\",\n            \"Description\": \"for gaming purposes\"\n        },\n        {\n            \"ID\": 12820,\n            \"Name\": \"gaming\",\n            \"Description\": \"for gaming purposes\"\n        },\n        {\n            \"ID\": 12822,\n            \"Name\": \"Accessories\",\n            \"Description\": \"to enhance appearance\"\n        },\n        {\n            \"ID\": 12823,\n            \"Name\": \"gaming\",\n            \"Description\": \"for gaming purposes\"\n        },\n        {\n            \"ID\": 12824,\n            \"Name\": \"Accessories\",\n            \"Description\": \"to enhance appearance\"\n        },\n        {\n            \"ID\": 12825,\n            \"Name\": \"Accessories\",\n            \"Description\": \"to enhance appearance\"\n        },\n        {\n            \"ID\": 12826,\n            \"Name\": \"gaming\",\n            \"Description\": \"for gaming purposes\"\n        },\n        {\n            \"ID\": 12827,\n            \"Name\": \"gaming\",\n            \"Description\": \"for gaming purposes\"\n        },\n        {\n            \"ID\": 12828,\n            \"Name\": \"gaming\",\n            \"Description\": \"for gaming purposes\"\n        },\n        {\n            \"ID\": 12829,\n            \"Name\": \"gaming\",\n            \"Description\": \"for gaming purposes\"\n        },\n        {\n            \"ID\": 12830,\n            \"Name\": \"gaming\",\n            \"Description\": \"\"\n        },\n        {\n            \"ID\": 12831,\n            \"Name\": \"gaming\",\n            \"Description\": \"for gaming purposes\"\n        },\n        {\n            \"ID\": 12832,\n            \"Name\": \"Accessories\",\n            \"Description\": \"to enhance appearance\"\n        },\n        {\n            \"ID\": 12836,\n            \"Name\": \"gaming\",\n            \"Description\": \"for gaming purposes\"\n        },\n        {\n            \"ID\": 12837,\n            \"Name\": \"Accessories\",\n            \"Description\": \"to enhance appearance\"\n        },\n        {\n            \"ID\": 12838,\n            \"Name\": \"gaming\",\n            \"Description\": \"for gaming purposes\"\n        },\n        {\n            \"ID\": 12839,\n            \"Name\": \"gaming\",\n            \"Description\": \"for gaming purposes\"\n        },\n        {\n            \"ID\": 12840,\n            \"Name\": \"gaming\",\n            \"Description\": \"for gaming purposes\"\n        },\n        {\n            \"ID\": 12841,\n            \"Name\": \"gaming\",\n            \"Description\": \"for gaming purposes\"\n        },\n        {\n            \"ID\": 12842,\n            \"Name\": \"gaming\",\n            \"Description\": \"for gaming purposes\"\n        },\n        {\n            \"ID\": 12843,\n            \"Name\": \"gaming\",\n            \"Description\": \"for gaming purposes\"\n        },\n        {\n            \"ID\": 12844,\n            \"Name\": \"gaming\",\n            \"Description\": \"for gaming purposes\"\n        },\n        {\n            \"ID\": 12845,\n            \"Name\": \"gaming\",\n            \"Description\": \"for gaming purposes\"\n        },\n        {\n            \"ID\": 12846,\n            \"Name\": \"Accessories\",\n            \"Description\": \"to enhance appearance\"\n        },\n        {\n            \"ID\": 12847,\n            \"Name\": \"gaming\",\n            \"Description\": \"for gaming purposes\"\n        },\n        {\n            \"ID\": 12848,\n            \"Name\": \"gaming\",\n            \"Description\": \"for gaming purposes\"\n        },\n        {\n            \"ID\": 12849,\n            \"Name\": \"gaming\",\n            \"Description\": \"for gaming purposes\"\n        },\n        {\n            \"ID\": 12850,\n            \"Name\": \"gaming\",\n            \"Description\": \"for gaming purposes\"\n        },\n        {\n            \"ID\": 12851,\n            \"Name\": \"!@#$%\",\n            \"Description\": \"for gaming purposes\"\n        },\n        {\n            \"ID\": 12853,\n            \"Name\": \"gaming\",\n            \"Description\": \"for gaming purposes\"\n        },\n        {\n            \"ID\": 12854,\n            \"Name\": \"gaming\",\n            \"Description\": \"for gaming purposes\"\n        },\n        {\n            \"ID\": 12855,\n            \"Name\": \"Accessories\",\n            \"Description\": \"to enhance appearance\"\n        },\n        {\n            \"ID\": 12856,\n            \"Name\": \"Accessories\",\n            \"Description\": \"to enhance appearance\"\n        },\n        {\n            \"ID\": 12857,\n            \"Name\": \"gaming\",\n            \"Description\": \"for gaming purposes\"\n        },\n        {\n            \"ID\": 12858,\n            \"Name\": \"!@#$%\",\n            \"Description\": \"for gaming purposes\"\n        },\n        {\n            \"ID\": 12860,\n            \"Name\": \"Accessories\",\n            \"Description\": \"to enhance appearance\"\n        },\n        {\n            \"ID\": 12861,\n            \"Name\": \"gaming\",\n            \"Description\": \"for gaming purposes\"\n        },\n        {\n            \"ID\": 12862,\n            \"Name\": \"gaming\",\n            \"Description\": \"for gaming purposes\"\n        },\n        {\n            \"ID\": 12863,\n            \"Name\": \"gaming\",\n            \"Description\": \"for gaming purposes\"\n        },\n        {\n            \"ID\": 12864,\n            \"Name\": \"!@#$%\",\n            \"Description\": \"for gaming purposes\"\n        },\n        {\n            \"ID\": 12866,\n            \"Name\": \"gaming\",\n            \"Description\": \"for gaming purposes\"\n        },\n        {\n            \"ID\": 12867,\n            \"Name\": \"!@#$%\",\n            \"Description\": \"for gaming purposes\"\n        },\n        {\n            \"ID\": 12869,\n            \"Name\": \"gaming\",\n            \"Description\": \"for gaming purposes\"\n        },\n        {\n            \"ID\": 12870,\n            \"Name\": \"!@#$%\",\n            \"Description\": \"for gaming purposes\"\n        },\n        {\n            \"ID\": 12872,\n            \"Name\": \"gaming\",\n            \"Description\": \"for gaming purposes\"\n        },\n        {\n            \"ID\": 12873,\n            \"Name\": \"!@#$%\",\n            \"Description\": \"for gaming purposes\"\n        },\n        {\n            \"ID\": 12875,\n            \"Name\": \"gaming\",\n            \"Description\": \"for gaming purposes\"\n        },\n        {\n            \"ID\": 12876,\n            \"Name\": \"!@#$%\",\n            \"Description\": \"for gaming purposes\"\n        },\n        {\n            \"ID\": 12878,\n            \"Name\": \"gaming\",\n            \"Description\": \"for gaming purposes\"\n        },\n        {\n            \"ID\": 12879,\n            \"Name\": \"!@#$%\",\n            \"Description\": \"for gaming purposes\"\n        },\n        {\n            \"ID\": 12881,\n            \"Name\": \"gaming\",\n            \"Description\": \"for gaming purposes\"\n        },\n        {\n            \"ID\": 12882,\n            \"Name\": \"!@#$%\",\n            \"Description\": \"for gaming purposes\"\n        },\n        {\n            \"ID\": 12884,\n            \"Name\": \"gaming\",\n            \"Description\": \"for gaming purposes\"\n        },\n        {\n            \"ID\": 12885,\n            \"Name\": \"gaming\",\n            \"Description\": \"for gaming purposes\"\n        },\n        {\n            \"ID\": 12886,\n            \"Name\": \"!@#$%\",\n            \"Description\": \"for gaming purposes\"\n        },\n        {\n            \"ID\": 12889,\n            \"Name\": \"!@#$%\",\n            \"Description\": \"for gaming purposes\"\n        },\n        {\n            \"ID\": 12891,\n            \"Name\": \"gaming\",\n            \"Description\": \"for gaming purposes\"\n        },\n        {\n            \"ID\": 12892,\n            \"Name\": \"!@#$%\",\n            \"Description\": \"for gaming purposes\"\n        },\n        {\n            \"ID\": 12894,\n            \"Name\": \"gaming\",\n            \"Description\": \"for gaming purposes\"\n        },\n        {\n            \"ID\": 12895,\n            \"Name\": \"!@#$%\",\n            \"Description\": \"for gaming purposes\"\n        },\n        {\n            \"ID\": 12897,\n            \"Name\": \"contoh-categories\",\n            \"Description\": \"Fashionable\"\n        },\n        {\n            \"ID\": 12898,\n            \"Name\": \"contoh-categories\",\n            \"Description\": \"contoh-categories\"\n        },\n        {\n            \"ID\": 12899,\n            \"Name\": \"gaming\",\n            \"Description\": \"for gaming purposes\"\n        },\n        {\n            \"ID\": 12901,\n            \"Name\": \"gaming\",\n            \"Description\": \"for gaming purposes\"\n        },\n        {\n            \"ID\": 12903,\n            \"Name\": \"gaming\",\n            \"Description\": \"for gaming purposes\"\n        },\n        {\n            \"ID\": 12905,\n            \"Name\": \"gaming\",\n            \"Description\": \"for gaming purposes\"\n        },\n        {\n            \"ID\": 12907,\n            \"Name\": \"gaming\",\n            \"Description\": \"for gaming purposes\"\n        },\n        {\n            \"ID\": 12909,\n            \"Name\": \"Gaming\",\n            \"Description\": \"For gaming purposes\"\n        },\n        {\n            \"ID\": 12910,\n            \"Name\": \"Gaming\",\n            \"Description\": \"\"\n        },\n        {\n            \"ID\": 12912,\n            \"Name\": \"Gaming\",\n            \"Description\": \"For gaming purposes\"\n        },\n        {\n            \"ID\": 12913,\n            \"Name\": \"Gaming\",\n            \"Description\": \"\"\n        },\n        {\n            \"ID\": 12915,\n            \"Name\": \"Gaming\",\n            \"Description\": \"For gaming purposes\"\n        },\n        {\n            \"ID\": 12916,\n            \"Name\": \"Gaming\",\n            \"Description\": \"\"\n        },\n        {\n            \"ID\": 12918,\n            \"Name\": \"gaming\",\n            \"Description\": \"for gaming purposes\"\n        },\n        {\n            \"ID\": 12919,\n            \"Name\": \"gaming\",\n            \"Description\": \"for gaming purposes\"\n        },\n        {\n            \"ID\": 12920,\n            \"Name\": \"gaming\",\n            \"Description\": \"for gaming purposes\"\n        },\n        {\n            \"ID\": 12921,\n            \"Name\": \"gaming\",\n            \"Description\": \"for gaming purposes\"\n        },\n        {\n            \"ID\": 12922,\n            \"Name\": \"gaming\",\n            \"Description\": \"for gaming purposes\"\n        },\n        {\n            \"ID\": 12923,\n            \"Name\": \"gaming\",\n            \"Description\": \"for gaming purposes\"\n        },\n        {\n            \"ID\": 12924,\n            \"Name\": \"gaming\",\n            \"Description\": \"for gaming purposes\"\n        },\n        {\n            \"ID\": 12926,\n            \"Name\": \"Gaming\",\n            \"Description\": \"For gaming purposes\"\n        },\n        {\n            \"ID\": 12927,\n            \"Name\": \"Gaming\",\n            \"Description\": \"\"\n        },\n        {\n            \"ID\": 12929,\n            \"Name\": \"gaming\",\n            \"Description\": \"for gaming purposes\"\n        },\n        {\n            \"ID\": 12931,\n            \"Name\": \"gaming\",\n            \"Description\": \"for gaming purposes\"\n        },\n        {\n            \"ID\": 12932,\n            \"Name\": \"Gaming\",\n            \"Description\": \"For gaming purposes\"\n        },\n        {\n            \"ID\": 12933,\n            \"Name\": \"Gaming\",\n            \"Description\": \"\"\n        },\n        {\n            \"ID\": 12935,\n            \"Name\": \"gaming\",\n            \"Description\": \"for gaming purposes\"\n        },\n        {\n            \"ID\": 12936,\n            \"Name\": \"gaming\",\n            \"Description\": \"for gaming purposes\"\n        },\n        {\n            \"ID\": 12938,\n            \"Name\": \"Gaming\",\n            \"Description\": \"For gaming purposes\"\n        },\n        {\n            \"ID\": 12939,\n            \"Name\": \"Gaming\",\n            \"Description\": \"\"\n        },\n        {\n            \"ID\": 12941,\n            \"Name\": \"Gaming\",\n            \"Description\": \"For gaming purposes\"\n        },\n        {\n            \"ID\": 12942,\n            \"Name\": \"Gaming\",\n            \"Description\": \"\"\n        },\n        {\n            \"ID\": 12944,\n            \"Name\": \"gaming\",\n            \"Description\": \"for gaming purposes\"\n        },\n        {\n            \"ID\": 12945,\n            \"Name\": \"gaming\",\n            \"Description\": \"for gaming purposes\"\n        },\n        {\n            \"ID\": 12946,\n            \"Name\": \"gaming\",\n            \"Description\": \"for gaming purposes\"\n        },\n        {\n            \"ID\": 12947,\n            \"Name\": \"gaming\",\n            \"Description\": \"for gaming purposes\"\n        },\n        {\n            \"ID\": 12948,\n            \"Name\": \"gaming\",\n            \"Description\": \"for gaming purposes\"\n        },\n        {\n            \"ID\": 12950,\n            \"Name\": \"gaming\",\n            \"Description\": \"for gaming purposes\"\n        },\n        {\n            \"ID\": 12952,\n            \"Name\": \"gaming\",\n            \"Description\": \"for gaming purposes\"\n        },\n        {\n            \"ID\": 12954,\n            \"Name\": \"gaming\",\n            \"Description\": \"for gaming purposes\"\n        },\n        {\n            \"ID\": 12955,\n            \"Name\": \"gaming\",\n            \"Description\": \"for gaming purposes\"\n        },\n        {\n            \"ID\": 12956,\n            \"Name\": \"gaming\",\n            \"Description\": \"for gaming purposes\"\n        },\n        {\n            \"ID\": 12957,\n            \"Name\": \"gaming\",\n            \"Description\": \"for gaming purposes\"\n        },\n        {\n            \"ID\": 12958,\n            \"Name\": \"gaming\",\n            \"Description\": \"for gaming purposes\"\n        },\n        {\n            \"ID\": 12962,\n            \"Name\": \"gaming\",\n            \"Description\": \"for gaming purposes\"\n        },\n        {\n            \"ID\": 12963,\n            \"Name\": \"gaming\",\n            \"Description\": \"for gaming purposes\"\n        },\n        {\n            \"ID\": 12966,\n            \"Name\": \"gaming\",\n            \"Description\": \"for gaming purposes\"\n        },\n        {\n            \"ID\": 12959,\n            \"Name\": \"Gaming\",\n            \"Description\": \"For gaming purposes\"\n        },\n        {\n            \"ID\": 12960,\n            \"Name\": \"Gaming\",\n            \"Description\": \"\"\n        },\n        {\n            \"ID\": 12964,\n            \"Name\": \"gaming\",\n            \"Description\": \"for gaming purposes\"\n        },\n        {\n            \"ID\": 12965,\n            \"Name\": \"gaming\",\n            \"Description\": \"for gaming purposes\"\n        },\n        {\n            \"ID\": 12967,\n            \"Name\": \"gaming\",\n            \"Description\": \"for gaming purposes\"\n        },\n        {\n            \"ID\": 12969,\n            \"Name\": \"testing product\",\n            \"Description\": \"this is the product description\"\n        },\n        {\n            \"ID\": 12970,\n            \"Name\": \"testing product\",\n            \"Description\": \"\"\n        },\n        {\n            \"ID\": 12972,\n            \"Name\": \"testing product\",\n            \"Description\": \"this is the product description\"\n        },\n        {\n            \"ID\": 12974,\n            \"Name\": \"gaming\",\n            \"Description\": \"for gaming purposes\"\n        },\n        {\n            \"ID\": 12975,\n            \"Name\": \"gaming\",\n            \"Description\": \"for gaming purposes\"\n        },\n        {\n            \"ID\": 12976,\n            \"Name\": \"gaming\",\n            \"Description\": \"for gaming purposes\"\n        },\n        {\n            \"ID\": 12977,\n            \"Name\": \"gaming\",\n            \"Description\": \"for gaming purposes\"\n        },\n        {\n            \"ID\": 12978,\n            \"Name\": \"gaming\",\n            \"Description\": \"for gaming purposes\"\n        },\n        {\n            \"ID\": 12979,\n            \"Name\": \"gaming\",\n            \"Description\": \"for gaming purposes\"\n        },\n        {\n            \"ID\": 12980,\n            \"Name\": \"gaming\",\n            \"Description\": \"for gaming purposes\"\n        },\n        {\n            \"ID\": 12981,\n            \"Name\": \"Cadmus Peverell\",\n            \"Description\": \"Hufflepuff\"\n        },\n        {\n            \"ID\": 12982,\n            \"Name\": \"Buckbeak\",\n            \"Description\": \"Slytherin\"\n        },\n        {\n            \"ID\": 12983,\n            \"Name\": \"George Weasley\",\n            \"Description\": \"Thunderbird\"\n        },\n        {\n            \"ID\": 12984,\n            \"Name\": \"gaming\",\n            \"Description\": \"for gaming purposes\"\n        },\n        {\n            \"ID\": 12986,\n            \"Name\": \"gaming\",\n            \"Description\": \"for gaming purposes\"\n        },\n        {\n            \"ID\": 12988,\n            \"Name\": \"gaming\",\n            \"Description\": \"for gaming purposes\"\n        },\n        {\n            \"ID\": 12990,\n            \"Name\": \"gaming\",\n            \"Description\": \"for gaming purposes\"\n        },\n        {\n            \"ID\": 12992,\n            \"Name\": \"gaming\",\n            \"Description\": \"for gaming purposes\"\n        },\n        {\n            \"ID\": 12994,\n            \"Name\": \"gaming\",\n            \"Description\": \"for gaming purposes\"\n        },\n        {\n            \"ID\": 12995,\n            \"Name\": \"gaming\",\n            \"Description\": \"for gaming purposes\"\n        },\n        {\n            \"ID\": 12996,\n            \"Name\": \"gaming\",\n            \"Description\": \"for gaming purposes\"\n        },\n        {\n            \"ID\": 12997,\n            \"Name\": \"gaming\",\n            \"Description\": \"for gaming purposes\"\n        },\n        {\n            \"ID\": 12998,\n            \"Name\": \"Akbar Rizky Fahrurozy\",\n            \"Description\": \"mini project\"\n        },\n        {\n            \"ID\": 12999,\n            \"Name\": \"Akbar Rizky Fahrurozy\",\n            \"Description\": \"mini project\"\n        },\n        {\n            \"ID\": 13000,\n            \"Name\": \"gaming\",\n            \"Description\": \"for gaming purposes\"\n        },\n        {\n            \"ID\": 13002,\n            \"Name\": \"Peripheral Gaming\",\n            \"Description\": \"Mouse, Keyboard, Headphone ETC\"\n        },\n        {\n            \"ID\": 13003,\n            \"Name\": \"gaming\",\n            \"Description\": \"for gaming purposes\"\n        },\n        {\n            \"ID\": 13004,\n            \"Name\": \"gaming\",\n            \"Description\": \"for gaming purposes\"\n        },\n        {\n            \"ID\": 13005,\n            \"Name\": \"gaming\",\n            \"Description\": \"for gaming purposes\"\n        },\n        {\n            \"ID\": 13006,\n            \"Name\": \"gaming\",\n            \"Description\": \"for gaming purposes\"\n        },\n        {\n            \"ID\": 13008,\n            \"Name\": \"gaming\",\n            \"Description\": \"for gaming purposes\"\n        },\n        {\n            \"ID\": 13010,\n            \"Name\": \"gaming\",\n            \"Description\": \"for gaming purposes\"\n        },\n        {\n            \"ID\": 13012,\n            \"Name\": \"gaming\",\n            \"Description\": \"for gaming purposes\"\n        },\n        {\n            \"ID\": 13014,\n            \"Name\": \"Gaming\",\n            \"Description\": \"For gaming purposes\"\n        },\n        {\n            \"ID\": 13015,\n            \"Name\": \"Gaming\",\n            \"Description\": \"\"\n        },\n        {\n            \"ID\": 13017,\n            \"Name\": \"gaming\",\n            \"Description\": \"for gaming purposes\"\n        },\n        {\n            \"ID\": 13019,\n            \"Name\": \"gaming\",\n            \"Description\": \"for gaming purposes\"\n        },\n        {\n            \"ID\": 13021,\n            \"Name\": \"Gaming\",\n            \"Description\": \"For gaming purposes\"\n        },\n        {\n            \"ID\": 13022,\n            \"Name\": \"Gaming\",\n            \"Description\": \"\"\n        },\n        {\n            \"ID\": 13024,\n            \"Name\": \"gaming\",\n            \"Description\": \"for gaming purposes\"\n        },\n        {\n            \"ID\": 13025,\n            \"Name\": \"furniture\",\n            \"Description\": \"\"\n        },\n        {\n            \"ID\": 13027,\n            \"Name\": \"gaming\",\n            \"Description\": \"for gaming purposes\"\n        },\n        {\n            \"ID\": 13029,\n            \"Name\": \"gaming\",\n            \"Description\": \"for gaming purposes\"\n        },\n        {\n            \"ID\": 13031,\n            \"Name\": \"gaming\",\n            \"Description\": \"for gaming purposes\"\n        },\n        {\n            \"ID\": 13032,\n            \"Name\": \"Peripheral Gaming\",\n            \"Description\": \"Mouse, Keyboard, Headphone ETC\"\n        },\n        {\n            \"ID\": 13033,\n            \"Name\": \"gaming\",\n            \"Description\": \"for gaming purposes\"\n        },\n        {\n            \"ID\": 13034,\n            \"Name\": \"gaming\",\n            \"Description\": \"for gaming purposes\"\n        },\n        {\n            \"ID\": 13035,\n            \"Name\": \"gaming\",\n            \"Description\": \"for gaming purposes\"\n        },\n        {\n            \"ID\": 13036,\n            \"Name\": \"gaming\",\n            \"Description\": \"for gaming purposes\"\n        },\n        {\n            \"ID\": 13037,\n            \"Name\": \"gaming\",\n            \"Description\": \"for gaming purposes\"\n        },\n        {\n            \"ID\": 13038,\n            \"Name\": \"gaming\",\n            \"Description\": \"for gaming purposes\"\n        },\n        {\n            \"ID\": 13039,\n            \"Name\": \"gaming\",\n            \"Description\": \"for gaming purposes\"\n        },\n        {\n            \"ID\": 13040,\n            \"Name\": \"gaming\",\n            \"Description\": \"for gaming purposes\"\n        },\n        {\n            \"ID\": 13042,\n            \"Name\": \"gaming\",\n            \"Description\": \"for gaming purposes\"\n        },\n        {\n            \"ID\": 13044,\n            \"Name\": \"gaming\",\n            \"Description\": \"for gaming purposes\"\n        },\n        {\n            \"ID\": 13046,\n            \"Name\": \"gaming\",\n            \"Description\": \"for gaming purposes\"\n        },\n        {\n            \"ID\": 13048,\n            \"Name\": \"gaming\",\n            \"Description\": \"for gaming purposes\"\n        },\n        {\n            \"ID\": 13050,\n            \"Name\": \"gaming\",\n            \"Description\": \"for gaming purposes\"\n        },\n        {\n            \"ID\": 13051,\n            \"Name\": \"gaming\",\n            \"Description\": \"for gaming purposes\"\n        },\n        {\n            \"ID\": 13053,\n            \"Name\": \"gaming\",\n            \"Description\": \"for gaming purposes\"\n        },\n        {\n            \"ID\": 13055,\n            \"Name\": \"gaming\",\n            \"Description\": \"for gaming purposes\"\n        },\n        {\n            \"ID\": 13057,\n            \"Name\": \"gaming\",\n            \"Description\": \"for gaming purposes\"\n        },\n        {\n            \"ID\": 13059,\n            \"Name\": \"gaming\",\n            \"Description\": \"for gaming purposes\"\n        },\n        {\n            \"ID\": 13060,\n            \"Name\": \"gaming\",\n            \"Description\": \"for gaming purposes\"\n        },\n        {\n            \"ID\": 13062,\n            \"Name\": \"gaming\",\n            \"Description\": \"for gaming purposes\"\n        },\n        {\n            \"ID\": 13064,\n            \"Name\": \"gaming\",\n            \"Description\": \"for gaming purposes\"\n        },\n        {\n            \"ID\": 13066,\n            \"Name\": \"gaming\",\n            \"Description\": \"for gaming purposes\"\n        },\n        {\n            \"ID\": 13068,\n            \"Name\": \"gaming\",\n            \"Description\": \"for gaming purposes\"\n        },\n        {\n            \"ID\": 13070,\n            \"Name\": \"gaming\",\n            \"Description\": \"for gaming purposes\"\n        },\n        {\n            \"ID\": 13071,\n            \"Name\": \"gaming\",\n            \"Description\": \"for gaming purposes\"\n        },\n        {\n            \"ID\": 13073,\n            \"Name\": \"gaming\",\n            \"Description\": \"for gaming purposes\"\n        },\n        {\n            \"ID\": 13074,\n            \"Name\": \"gaming\",\n            \"Description\": \"for gaming purposes\"\n        },\n        {\n            \"ID\": 13075,\n            \"Name\": \"gaming\",\n            \"Description\": \"for gaming purposes\"\n        },\n        {\n            \"ID\": 13078,\n            \"Name\": \"gaming\",\n            \"Description\": \"for gaming purposes\"\n        },\n        {\n            \"ID\": 13079,\n            \"Name\": \"gaming\",\n            \"Description\": \"for gaming purposes\"\n        },\n        {\n            \"ID\": 13081,\n            \"Name\": \"Gaming\",\n            \"Description\": \"For gaming purposes\"\n        },\n        {\n            \"ID\": 13082,\n            \"Name\": \"Gaming\",\n            \"Description\": \"\"\n        },\n        {\n            \"ID\": 13084,\n            \"Name\": \"Gaming\",\n            \"Description\": \"For gaming purposes\"\n        },\n        {\n            \"ID\": 13085,\n            \"Name\": \"Gaming\",\n            \"Description\": \"\"\n        },\n        {\n            \"ID\": 13087,\n            \"Name\": \"Furniture\",\n            \"Description\": \"Furniture Jepara\"\n        },\n        {\n            \"ID\": 13089,\n            \"Name\": \"Furniture\",\n            \"Description\": \"Furniture Jepara\"\n        },\n        {\n            \"ID\": 13091,\n            \"Name\": \"gaming\",\n            \"Description\": \"for gaming purposes\"\n        },\n        {\n            \"ID\": 13093,\n            \"Name\": \"gaming\",\n            \"Description\": \"for gaming purposes\"\n        },\n        {\n            \"ID\": 13095,\n            \"Name\": \"gaming\",\n            \"Description\": \"for gaming purposes\"\n        },\n        {\n            \"ID\": 13097,\n            \"Name\": \"gaming\",\n            \"Description\": \"for gaming purposes\"\n        },\n        {\n            \"ID\": 13099,\n            \"Name\": \"gaming\",\n            \"Description\": \"for gaming purposes\"\n        },\n        {\n            \"ID\": 13100,\n            \"Name\": \"gaming\",\n            \"Description\": \"\"\n        },\n        {\n            \"ID\": 13104,\n            \"Name\": \"gaming\",\n            \"Description\": \"for gaming purposes\"\n        },\n        {\n            \"ID\": 13105,\n            \"Name\": \"gaming\",\n            \"Description\": \"\"\n        },\n        {\n            \"ID\": 13109,\n            \"Name\": \"gaming\",\n            \"Description\": \"for gaming purposes\"\n        },\n        {\n            \"ID\": 13111,\n            \"Name\": \"gaming\",\n            \"Description\": \"for gaming purposes\"\n        },\n        {\n            \"ID\": 13113,\n            \"Name\": \"gaming\",\n            \"Description\": \"for gaming purposes\"\n        },\n        {\n            \"ID\": 13115,\n            \"Name\": \"DICOBA YAH\",\n            \"Description\": \"API WORKS\"\n        },\n        {\n            \"ID\": 13116,\n            \"Name\": \"gaming\",\n            \"Description\": \"for gaming purposes\"\n        },\n        {\n            \"ID\": 13118,\n            \"Name\": \"DICOBA YAH\",\n            \"Description\": \"API WORKS\"\n        },\n        {\n            \"ID\": 13119,\n            \"Name\": \"gaming\",\n            \"Description\": \"for gaming purposes\"\n        },\n        {\n            \"ID\": 13121,\n            \"Name\": \"gaming\",\n            \"Description\": \"for gaming purposes\"\n        },\n        {\n            \"ID\": 13123,\n            \"Name\": \"gaming\",\n            \"Description\": \"for gaming purposes\"\n        },\n        {\n            \"ID\": 13125,\n            \"Name\": \"gaming\",\n            \"Description\": \"for gaming purposes\"\n        },\n        {\n            \"ID\": 13126,\n            \"Name\": \"gaming\",\n            \"Description\": \"for gaming purposes\"\n        },\n        {\n            \"ID\": 13127,\n            \"Name\": \"gaming\",\n            \"Description\": \"for gaming purposes\"\n        },\n        {\n            \"ID\": 13128,\n            \"Name\": \"gaming\",\n            \"Description\": \"for gaming purposes\"\n        },\n        {\n            \"ID\": 13130,\n            \"Name\": \"gaming\",\n            \"Description\": \"for gaming purposes\"\n        },\n        {\n            \"ID\": 13131,\n            \"Name\": \"gaming\",\n            \"Description\": \"\"\n        },\n        {\n            \"ID\": 13135,\n            \"Name\": \"Meowth\",\n            \"Description\": \"Maxime vel minus id non ipsam voluptatem similique.\"\n        },\n        {\n            \"ID\": 13136,\n            \"Name\": \"gaming\",\n            \"Description\": \"for gaming purposes\"\n        },\n        {\n            \"ID\": 13137,\n            \"Name\": \"gaming\",\n            \"Description\": \"\"\n        },\n        {\n            \"ID\": 13141,\n            \"Name\": \"gaming\",\n            \"Description\": \"for gaming purposes\"\n        },\n        {\n            \"ID\": 13142,\n            \"Name\": \"gaming\",\n            \"Description\": \"\"\n        },\n        {\n            \"ID\": 13146,\n            \"Name\": \"gaming\",\n            \"Description\": \"for gaming purposes\"\n        },\n        {\n            \"ID\": 13147,\n            \"Name\": \"gaming\",\n            \"Description\": \"\"\n        },\n        {\n            \"ID\": 13151,\n            \"Name\": \"gaming\",\n            \"Description\": \"for gaming purposes\"\n        },\n        {\n            \"ID\": 13152,\n            \"Name\": \"gaming\",\n            \"Description\": \"for gaming purposes\"\n        },\n        {\n            \"ID\": 13153,\n            \"Name\": \"gaming\",\n            \"Description\": \"for gaming purposes\"\n        },\n        {\n            \"ID\": 13154,\n            \"Name\": \"gaming\",\n            \"Description\": \"\"\n        },\n        {\n            \"ID\": 13158,\n            \"Name\": \"gaming\",\n            \"Description\": \"for gaming purposes\"\n        },\n        {\n            \"ID\": 13159,\n            \"Name\": \"gaming\",\n            \"Description\": \"\"\n        },\n        {\n            \"ID\": 13164,\n            \"Name\": \"gaming\",\n            \"Description\": \"for gaming purposes\"\n        },\n        {\n            \"ID\": 13166,\n            \"Name\": \"DICOBA YAH\",\n            \"Description\": \"API WORKS\"\n        },\n        {\n            \"ID\": 13167,\n            \"Name\": \"gaming\",\n            \"Description\": \"for gaming purposes\"\n        },\n        {\n            \"ID\": 13169,\n            \"Name\": \"gaming\",\n            \"Description\": \"for gaming purposes\"\n        },\n        {\n            \"ID\": 13171,\n            \"Name\": \"gaming\",\n            \"Description\": \"for gaming purposes\"\n        },\n        {\n            \"ID\": 13172,\n            \"Name\": \"gaming\",\n            \"Description\": \"for gaming purposes\"\n        },\n        {\n            \"ID\": 13173,\n            \"Name\": \"gaming\",\n            \"Description\": \"for gaming purposes\"\n        },\n        {\n            \"ID\": 13174,\n            \"Name\": \"gaming\",\n            \"Description\": \"\"\n        },\n        {\n            \"ID\": 13178,\n            \"Name\": \"Gaming\",\n            \"Description\": \"For gaming purposes\"\n        },\n        {\n            \"ID\": 13179,\n            \"Name\": \"Gaming\",\n            \"Description\": \"\"\n        },\n        {\n            \"ID\": 13181,\n            \"Name\": \"Gaming\",\n            \"Description\": \"For gaming purposes\"\n        },\n        {\n            \"ID\": 13182,\n            \"Name\": \"Gaming\",\n            \"Description\": \"\"\n        },\n        {\n            \"ID\": 13184,\n            \"Name\": \"Gaming\",\n            \"Description\": \"For gaming purposes\"\n        },\n        {\n            \"ID\": 13185,\n            \"Name\": \"Gaming\",\n            \"Description\": \"\"\n        },\n        {\n            \"ID\": 13187,\n            \"Name\": \"Gaming\",\n            \"Description\": \"For gaming purposes\"\n        },\n        {\n            \"ID\": 13188,\n            \"Name\": \"Gaming\",\n            \"Description\": \"\"\n        },\n        {\n            \"ID\": 13190,\n            \"Name\": \"Gaming\",\n            \"Description\": \"For gaming purposes\"\n        },\n        {\n            \"ID\": 13191,\n            \"Name\": \"Gaming\",\n            \"Description\": \"\"\n        },\n        {\n            \"ID\": 13193,\n            \"Name\": \"Gaming\",\n            \"Description\": \"For gaming purposes\"\n        },\n        {\n            \"ID\": 13194,\n            \"Name\": \"Gaming\",\n            \"Description\": \"\"\n        },\n        {\n            \"ID\": 13196,\n            \"Name\": \"Category Aulia\",\n            \"Description\": \"ini category aulia\"\n        },\n        {\n            \"ID\": 13197,\n            \"Name\": \"Gaming\",\n            \"Description\": \"For gaming purposes\"\n        },\n        {\n            \"ID\": 13198,\n            \"Name\": \"Gaming\",\n            \"Description\": \"\"\n        },\n        {\n            \"ID\": 13200,\n            \"Name\": \"Gaming\",\n            \"Description\": \"For gaming purposes\"\n        },\n        {\n            \"ID\": 13201,\n            \"Name\": \"Gaming\",\n            \"Description\": \"\"\n        },\n        {\n            \"ID\": 13203,\n            \"Name\": \"Gaming\",\n            \"Description\": \"For gaming purposes\"\n        },\n        {\n            \"ID\": 13204,\n            \"Name\": \"Gaming\",\n            \"Description\": \"\"\n        },\n        {\n            \"ID\": 13206,\n            \"Name\": \"Gaming\",\n            \"Description\": \"For gaming purposes\"\n        },\n        {\n            \"ID\": 13207,\n            \"Name\": \"Gaming\",\n            \"Description\": \"\"\n        },\n        {\n            \"ID\": 13209,\n            \"Name\": \"Gaming\",\n            \"Description\": \"For gaming purposes\"\n        },\n        {\n            \"ID\": 13210,\n            \"Name\": \"Gaming\",\n            \"Description\": \"\"\n        },\n        {\n            \"ID\": 13212,\n            \"Name\": \"Gaming\",\n            \"Description\": \"For gaming purposes\"\n        },\n        {\n            \"ID\": 13213,\n            \"Name\": \"Gaming\",\n            \"Description\": \"\"\n        },\n        {\n            \"ID\": 13215,\n            \"Name\": \"gaming\",\n            \"Description\": \"for gaming purposes\"\n        },\n        {\n            \"ID\": 13217,\n            \"Name\": \"Gaming\",\n            \"Description\": \"For gaming purposes\"\n        },\n        {\n            \"ID\": 13218,\n            \"Name\": \"Gaming\",\n            \"Description\": \"\"\n        },\n        {\n            \"ID\": 13220,\n            \"Name\": \"Gaming\",\n            \"Description\": \"For gaming purposes\"\n        },\n        {\n            \"ID\": 13221,\n            \"Name\": \"Gaming\",\n            \"Description\": \"\"\n        },\n        {\n            \"ID\": 13223,\n            \"Name\": \"cake2\",\n            \"Description\": \"cake lapis\"\n        },\n        {\n            \"ID\": 13224,\n            \"Name\": \"Furniture\",\n            \"Description\": \"Furniture Jepara\"\n        },\n        {\n            \"ID\": 13226,\n            \"Name\": \"Furniture\",\n            \"Description\": \"Furniture Jepara\"\n        },\n        {\n            \"ID\": 13228,\n            \"Name\": \"gaming\",\n            \"Description\": \"for gaming purposes\"\n        }\n    ]\n}","statusCode":200},"precondition":false,"level":2}]}]},{"number":7,"description":"Then I receive valid HTTP response code 200 for GET All product category","duration":17,"startTime":"2023-05-07T12:04:11.290337900+07:00[Asia/Jakarta]","result":"SUCCESS","precondition":false,"level":0,"children":[{"number":8,"description":"I receive valid HTTP response code 200 for GET All product category","duration":2,"startTime":"2023-05-07T12:04:11.303302600+07:00[Asia/Jakarta]","result":"SUCCESS","precondition":false,"level":1}]},{"number":9,"description":"And I received valid data for all product category","duration":7,"startTime":"2023-05-07T12:04:11.310284800+07:00[Asia/Jakarta]","result":"SUCCESS","precondition":false,"level":0,"children":[{"number":10,"description":"I received valid data for all product category","duration":1,"startTime":"2023-05-07T12:04:11.313278100+07:00[Asia/Jakarta]","result":"SUCCESS","precondition":false,"level":1}]}],"userStory":{"id":"category","storyName":"category","displayName":"category","path":"file:///E:/mini%20peoject/RestAPi/src/test/resources/api/productcategory.feature","type":"feature","qualifiedTag":{"name":"Api/category","type":"feature","displayName":"Api/category"}},"featureTag":{"name":"Api/category","type":"feature","displayName":"Api/category"},"title":"GET  list of category","description":"","allTags":[{"name":"Api/category","type":"feature","displayName":"Api/category"}],"startTime":"2023-05-07T12:04:10.847522200+07:00[Asia/Jakarta]","duration":471,"projectKey":"","isManualTestingUpToDate":false,"manual":false,"testSource":"Cucumber","result":"SUCCESS"}